chaosorg/__init__.py
chaosorg/cli.py
chaosorg/organizer.py
chaosorg/undo.py
chaosorg-0.1.1.dist-info/licenses/LICENSE
chaosorg-0.1.1.dist-info/METADATA
chaosorg-0.1.1.dist-info/WHEEL
chaosorg-0.1.1.dist-info/entry_points.txt
chaosorg-0.1.1.dist-info/top_level.txt
chaosorg-0.1.1.dist-info/RECORD
