Metadata-Version: 2.4
Name: chaosorg
Version: 0.1.1
Summary: A CLI tool to organize messy data science project folders
Home-page: https://github.com/chrisjaimyantony/chaosorg
Author: Chris Jaimy Antony
Author-email: Chris Jaimy Antony <chrisjaimyantony@email.com>
License: MIT License
Classifier: Programming Language :: Python :: 3
Classifier: License :: OSI Approved :: MIT License
Classifier: Operating System :: OS Independent
Requires-Python: >=3.7
License-File: LICENSE
Requires-Dist: typer[all]
Dynamic: author
Dynamic: home-page
Dynamic: license-file
Dynamic: requires-python
